gx_sqlalchemy_redshift-0.8.20.dist-info/licenses/LICENSE
redshift_sqlalchemy/__init__.py
sqlalchemy_redshift/__init__.py
sqlalchemy_redshift/commands.py
sqlalchemy_redshift/ddl.py
sqlalchemy_redshift/dialect.py
sqlalchemy_redshift/redshift-ca-bundle.crt
gx_sqlalchemy_redshift-0.8.20.dist-info/METADATA
gx_sqlalchemy_redshift-0.8.20.dist-info/WHEEL
gx_sqlalchemy_redshift-0.8.20.dist-info/entry_points.txt
gx_sqlalchemy_redshift-0.8.20.dist-info/top_level.txt
gx_sqlalchemy_redshift-0.8.20.dist-info/RECORD
